g42cloudsdkcore/__init__.py
g42cloudsdkcore/client.py
g42cloudsdkcore/sdk_request.py
g42cloudsdkcore/sdk_response.py
g42cloudsdkcore/sdk_stream_request.py
g42cloudsdkcore/sdk_stream_response.py
g42cloudsdkcore/auth/__init__.py
g42cloudsdkcore/auth/cache.py
g42cloudsdkcore/auth/credentials.py
g42cloudsdkcore/auth/internal.py
g42cloudsdkcore/auth/provider.py
g42cloudsdkcore/exceptions/__init__.py
g42cloudsdkcore/exceptions/exception_handler.py
g42cloudsdkcore/exceptions/exceptions.py
g42cloudsdkcore/http/__init__.py
g42cloudsdkcore/http/formdata.py
g42cloudsdkcore/http/future_session.py
g42cloudsdkcore/http/http_client.py
g42cloudsdkcore/http/http_config.py
g42cloudsdkcore/http/http_handler.py
g42cloudsdkcore/http/primitive_types.py
g42cloudsdkcore/http/progress.py
g42cloudsdkcore/region/__init__.py
g42cloudsdkcore/region/cache.py
g42cloudsdkcore/region/provider.py
g42cloudsdkcore/region/region.py
g42cloudsdkcore/signer/__init__.py
g42cloudsdkcore/signer/algorithm.py
g42cloudsdkcore/signer/gm.py
g42cloudsdkcore/signer/hkdf.py
g42cloudsdkcore/signer/signer.py
g42cloudsdkcore/utils/__init__.py
g42cloudsdkcore/utils/core_utils.py
g42cloudsdkcore/utils/filepath_utils.py
g42cloudsdkcore/utils/http_utils.py
g42cloudsdkcore/utils/six_utils.py
g42cloudsdkcore/utils/string_utils.py
g42cloudsdkcore/utils/time_utils.py
g42cloudsdkcore/utils/xml_utils.py
g42cloudsdkcore-0.0.10b0.dist-info/LICENSE
g42cloudsdkcore-0.0.10b0.dist-info/METADATA
g42cloudsdkcore-0.0.10b0.dist-info/WHEEL
g42cloudsdkcore-0.0.10b0.dist-info/top_level.txt
g42cloudsdkcore-0.0.10b0.dist-info/RECORD
